MANIFEST.in
README
README.md
setup.py
rpgtools/__init__.py
rpgtools/items.json
rpgtools/loot.py
rpgtools.egg-info/PKG-INFO
rpgtools.egg-info/SOURCES.txt
rpgtools.egg-info/dependency_links.txt
rpgtools.egg-info/top_level.txt