Metadata-Version: 1.1
Name: rpgtools
Version: 0.4a.1
Summary: Rpgtools consist in a set of programs/tools usefull for
Home-page: https://github.com/gcavalcante8808/rpgtools
Author: Gabriel Abdalla Cavalcante
Author-email: gabriel.cavalcante88@gmail.com
License: License :: OSI Approved :: Apache Software License
Platform: UNKNOWN
Classifier: Development Status :: 3 - Alpha
Classifier: Intended Audience :: Information Technology
Classifier: Intended Audience :: System Administrators
Classifier: Intended Audience :: End Users/Desktop
Classifier: License :: OSI Approved :: Apache Software License
Classifier: Programming Language :: Python
Classifier: Programming Language :: Python :: 3
Classifier: Programming Language :: Python :: 2
